MilanoteUnofficialApi/__init__.py
MilanoteUnofficialApi/exceptions.py
MilanoteUnofficialApi/milanote.py
MilanoteUnofficialApi/elements/__init__.py
MilanoteUnofficialApi/elements/annotation.py
MilanoteUnofficialApi/elements/board.py
MilanoteUnofficialApi/elements/card.py
MilanoteUnofficialApi/elements/color_swatch.py
MilanoteUnofficialApi/elements/column.py
MilanoteUnofficialApi/elements/comment.py
MilanoteUnofficialApi/elements/commentthread.py
MilanoteUnofficialApi/elements/document.py
MilanoteUnofficialApi/elements/element.py
MilanoteUnofficialApi/elements/file.py
MilanoteUnofficialApi/elements/image.py
MilanoteUnofficialApi/elements/link.py
MilanoteUnofficialApi/elements/location.py
MilanoteUnofficialApi/elements/meta.py
MilanoteUnofficialApi/elements/sketch.py
MilanoteUnofficialApi/elements/task.py
MilanoteUnofficialApi/elements/tasklist.py
milanote_unofficial_api-1.0.0.dist-info/LICENSE
milanote_unofficial_api-1.0.0.dist-info/METADATA
milanote_unofficial_api-1.0.0.dist-info/WHEEL
milanote_unofficial_api-1.0.0.dist-info/top_level.txt
milanote_unofficial_api-1.0.0.dist-info/RECORD
