Metadata-Version: 2.1
Name: milanote-unofficial-api
Version: 1.0.0
Summary: The Unofficial Milanote API in Python.
Home-page: https://github.com/SerhanCeetin/Milanote-Unofficial-API
Download-URL: https://github.com/SerhanCeetin/Milanote-Unofficial-API/tarball/master
Author: Serhan Çetin
Author-email: ceetinserhan@gmail.com
License: MIT
Keywords: milanote,python3,api,unofficial,milanote-api,milanote api
Classifier: Development Status :: 4 - Beta
Classifier: Intended Audience :: Developers
Classifier: Topic :: Home Automation
Classifier: Topic :: Software Development :: Build Tools
Classifier: Topic :: Software Development :: Libraries :: Python Modules
Classifier: License :: OSI Approved :: MIT License
Classifier: Programming Language :: Python :: 3.7
Classifier: Programming Language :: Python :: 3.8
Classifier: Programming Language :: Python :: 3.9
Classifier: Programming Language :: Python :: 3.10
Classifier: Programming Language :: Python :: 3.11
License-File: LICENSE
Requires-Dist: requests
